<?xml version="1.0" encoding="UTF-8"?>
<objects serializationModel="Studio.02.01.00">
	<object class="AudioFile" id="{c3035134-a895-4748-b0fa-2a789fb01ffe}">
		<property name="assetPath">
			<value>Swap - Trimmed.wav</value>
		</property>
		<property name="frequencyInKHz">
			<value>44.0999985</value>
		</property>
		<property name="channelCount">
			<value>2</value>
		</property>
		<property name="length">
			<value>0.19</value>
		</property>
		<relationship name="masterAssetFolder">
			<destination>{3c4736cf-da7e-4af5-b36d-618217c2572f}</destination>
		</relationship>
	</object>
</objects>
